azure_pipelines_validator/__init__.py
azure_pipelines_validator/azure_cli.py
azure_pipelines_validator/azure_devops.py
azure_pipelines_validator/cli.py
azure_pipelines_validator/exceptions.py
azure_pipelines_validator/file_scanner.py
azure_pipelines_validator/models.py
azure_pipelines_validator/reporter.py
azure_pipelines_validator/schema_engine.py
azure_pipelines_validator/schema_sources.py
azure_pipelines_validator/service.py
azure_pipelines_validator/settings.py
azure_pipelines_validator/yaml_processing.py
azure_pipelines_validator/yamllint_engine.py
azure_pipeline_validator-0.2.1.dist-info/METADATA
azure_pipeline_validator-0.2.1.dist-info/WHEEL
azure_pipeline_validator-0.2.1.dist-info/entry_points.txt
azure_pipeline_validator-0.2.1.dist-info/licenses/LICENSE
azure_pipeline_validator-0.2.1.dist-info/RECORD
