Metadata-Version: 2.4
Name: azure-pipeline-validator
Version: 0.2.1
Summary: Comprehensive Azure DevOps YAML validator
Project-URL: homepage, https://github.com/andrewmaspero/azure-pipeline-validator
Project-URL: repository, https://github.com/andrewmaspero/azure-pipeline-validator
Project-URL: issues, https://github.com/andrewmaspero/azure-pipeline-validator/issues
Author-email: Andrew Maspero <andrew@maspero.co>
License: MIT
License-File: LICENSE
Keywords: azure,devops,pipelines,validator,yaml
Classifier: Development Status :: 4 - Beta
Classifier: Intended Audience :: Developers
Classifier: License :: OSI Approved :: MIT License
Classifier: Programming Language :: Python :: 3
Classifier: Programming Language :: Python :: 3.13
Classifier: Topic :: Software Development :: Build Tools
Requires-Python: >=3.13
Requires-Dist: httpx>=0.28.1
Requires-Dist: jsonschema>=4.25.1
Requires-Dist: keyring>=25.5.0
Requires-Dist: pydantic>=2.12.4
Requires-Dist: pyyaml>=6.0.3
Requires-Dist: rich>=14.2.0
Requires-Dist: typer>=0.20.0
Requires-Dist: yamllint>=1.37.1
